zephyr_jira_linker/__init__.py
zephyr_jira_linker/main.py
zephyr_jira_linker-0.1.2.dist-info/licenses/LICENSE
zephyr_jira_linker-0.1.2.dist-info/METADATA
zephyr_jira_linker-0.1.2.dist-info/WHEEL
zephyr_jira_linker-0.1.2.dist-info/entry_points.txt
zephyr_jira_linker-0.1.2.dist-info/top_level.txt
zephyr_jira_linker-0.1.2.dist-info/RECORD
