Metadata-Version: 2.4
Name: zephyr-jira-linker
Version: 0.1.2
Summary: A command-line tool for linking test cases in Zephyr Scale to Jira issues
Home-page: https://github.com/yourusername/zephyr-test-linker
Author: Pandiyaraj Karuppasamy
Author-email: Pandiyaraj Karuppasamy <pandiyarajk@live.com>
Maintainer-email: Pandiyaraj Karuppasamy <pandiyarajk@live.com>
License-Expression: MIT
Project-URL: Homepage, https://github.com/pandiyarajk/zephyr-jira-linker
Project-URL: Documentation, https://github.com/pandiyarajk/zephyr-jira-linker#readme
Project-URL: Repository, https://github.com/pandiyarajk/zephyr-jira-linker.git
Project-URL: Issues, https://github.com/pandiyarajk/zephyr-jira-linker/issues
Project-URL: Changelog, https://github.com/pandiyarajk/zephyr-jira-linker/blob/main/CHANGE_LOG.md
Keywords: zephyr,jira,test-management,automation,devops
Classifier: Development Status :: 4 - Beta
Classifier: Intended Audience :: Developers
Classifier: Operating System :: OS Independent
Classifier: Programming Language :: Python :: 3
Classifier: Programming Language :: Python :: 3.7
Classifier: Programming Language :: Python :: 3.8
Classifier: Programming Language :: Python :: 3.9
Classifier: Programming Language :: Python :: 3.10
Classifier: Programming Language :: Python :: 3.11
Classifier: Programming Language :: Python :: 3.12
Classifier: Topic :: Software Development :: Testing
Classifier: Topic :: Software Development :: Quality Assurance
Requires-Python: >=3.7
License-File: LICENSE
Requires-Dist: requests>=2.25.0
Dynamic: author
Dynamic: home-page
Dynamic: license-file
Dynamic: requires-python
